manifold_fabric_utils/__init__.py
manifold_fabric_utils/utils.py
manifold_fabric_utils-0.1.0.dist-info/licenses/LICENSE
manifold_fabric_utils-0.1.0.dist-info/METADATA
manifold_fabric_utils-0.1.0.dist-info/WHEEL
manifold_fabric_utils-0.1.0.dist-info/top_level.txt
manifold_fabric_utils-0.1.0.dist-info/RECORD
