Metadata-Version: 2.4
Name: manifold_fabric_utils
Version: 0.1.0
Summary: Utilities for Fabric/Spark environments
Home-page: https://bitbucket.org/digintent/fabric-utils/src
Author: Patrick Dwyer
Author-email: patrick.dwyer@manifold.group
Classifier: Programming Language :: Python :: 3
Classifier: License :: OSI Approved :: MIT License
Classifier: Operating System :: OS Independent
Requires-Python: >=3.6
License-File: LICENSE
Dynamic: author
Dynamic: author-email
Dynamic: classifier
Dynamic: description
Dynamic: description-content-type
Dynamic: home-page
Dynamic: license-file
Dynamic: requires-python
Dynamic: summary
